{"v":"5.8.1","fr":25,"ip":0,"op":41,"w":330,"h":500,"nm":"E","ddd":0,"assets":[],"layers":[{"ddd":0,"ind":1,"ty":4,"nm":"Color 02","sr":1,"ks":{"o":{"a":0,"k":0,"ix":11},"r":{"a":0,"k":0,"ix":10},"p":{"a":0,"k":[54.22,179.935,0],"ix":2,"l":2},"a":{"a":0,"k":[-191,-198,0],"ix":1,"l":2},"s":{"a":0,"k":[81,81,100],"ix":6,"l":2}},"ao":0,"shapes":[{"ty":"gr","it":[{"ty":"rc","d":1,"s":{"a":0,"k":[42,42],"ix":2},"p":{"a":0,"k":[0,0],"ix":3},"r":{"a":0,"k":0,"ix":4},"nm":"Rectangle Path 1","mn":"ADBE Vector Shape - Rect","hd":false},{"ty":"fl","c":{"a":0,"k":[0,0.188235294118,0.301960784314,1],"ix":4},"o":{"a":0,"k":100,"ix":5},"r":1,"bm":0,"nm":"Fill 1","mn":"ADBE Vector Graphic - Fill","hd":false},{"ty":"tr","p":{"a":0,"k":[-191,-198],"ix":2},"a":{"a":0,"k":[0,0],"ix":1},"s":{"a":0,"k":[100,100],"ix":3},"r":{"a":0,"k":0,"ix":6},"o":{"a":0,"k":100,"ix":7},"sk":{"a":0,"k":0,"ix":4},"sa":{"a":0,"k":0,"ix":5},"nm":"Transform"}],"nm":"Rectangle 1","np":3,"cix":2,"bm":0,"ix":1,"mn":"ADBE Vector Group","hd":false}],"ip":0,"op":41,"st":0,"bm":0},{"ddd":0,"ind":2,"ty":4,"nm":"Splash_4_Down","sr":1,"ks":{"o":{"a":0,"k":100,"ix":11},"r":{"a":0,"k":0,"ix":10},"p":{"a":0,"k":[298.719,315.812,0],"ix":2,"l":2},"a":{"a":0,"k":[0,0,0],"ix":1,"l":2},"s":{"a":0,"k":[59.13,59.13,100],"ix":6,"l":2}},"ao":0,"shapes":[{"ty":"gr","it":[{"ind":0,"ty":"sh","ix":1,"ks":{"a":1,"k":[{"i":{"x":0.833,"y":0.833},"o":{"x":0.167,"y":0.167},"t":14,"s":[{"i":[[0,0],[-5.823,-14.538],[-0.442,-3.634],[-1.232,7.916]],"o":[[0,0],[3.535,8.825],[0.712,5.849],[3.489,-22.414]],"v":[[-262.873,15.182],[-267.068,29.435],[-254.812,43.36],[-256.175,34.572]],"c":true}]},{"i":{"x":0.833,"y":0.833},"o":{"x":0.167,"y":0.167},"t":15,"s":[{"i":[[0,0],[-1.707,-10.054],[0,0],[0.562,9.375]],"o":[[0,0],[1.125,6.625],[0,0],[-0.593,-9.888]],"v":[[-269.812,33.125],[-275.5,44],[-267.75,49],[-263.688,40.75]],"c":true}]},{"t":16,"s":[{"i":[[0,0],[-0.375,-5.625],[0,0],[0.037,3.125]],"o":[[0,0],[0.447,6.705],[0,0],[-0.062,-5.25]],"v":[[-269.812,33.125],[-273.75,38.25],[-269.5,40.875],[-266.312,36.75]],"c":true}]}],"ix":2},"nm":"Path 1","mn":"ADBE Vector Shape - Group","hd":false},{"ty":"st","c":{"a":0,"k":[0,0.188235294118,0.301960784314,1],"ix":3},"o":{"a":0,"k":100,"ix":4},"w":{"a":0,"k":0,"ix":5},"lc":1,"lj":1,"ml":4,"bm":0,"nm":"Stroke 1","mn":"ADBE Vector Graphic - Stroke","hd":false},{"ty":"fl","c":{"a":0,"k":[0,0.188235294118,0.301960784314,1],"ix":4},"o":{"a":0,"k":100,"ix":5},"r":1,"bm":0,"nm":"Fill 1","mn":"ADBE Vector Graphic - Fill","hd":false},{"ty":"tr","p":{"a":0,"k":[0,0],"ix":2},"a":{"a":0,"k":[0,0],"ix":1},"s":{"a":0,"k":[100,100],"ix":3},"r":{"a":0,"k":0,"ix":6},"o":{"a":0,"k":100,"ix":7},"sk":{"a":0,"k":0,"ix":4},"sa":{"a":0,"k":0,"ix":5},"nm":"Transform"}],"nm":"Shape 1","np":3,"cix":2,"bm":0,"ix":1,"mn":"ADBE Vector Group","hd":false}],"ip":13,"op":17,"st":-21,"bm":0},{"ddd":0,"ind":3,"ty":4,"nm":"Splash_3_Down","sr":1,"ks":{"o":{"a":0,"k":100,"ix":11},"r":{"a":0,"k":0,"ix":10},"p":{"a":0,"k":[296.694,315.812,0],"ix":2,"l":2},"a":{"a":0,"k":[0,0,0],"ix":1,"l":2},"s":{"a":0,"k":[59.13,59.13,100],"ix":6,"l":2}},"ao":0,"shapes":[{"ty":"gr","it":[{"ind":0,"ty":"sh","ix":1,"ks":{"a":1,"k":[{"i":{"x":0.833,"y":0.833},"o":{"x":0.167,"y":0.167},"t":16,"s":[{"i":[[8.823,-0.882],[-6.125,-10],[-0.5,2.75]],"o":[[-2.5,0.25],[6.125,10],[0.5,-2.75]],"v":[[-271.125,-52.875],[-274.875,-42.125],[-263.75,-43]],"c":true}]},{"t":17,"s":[{"i":[[4,0.625],[-1.625,-2.75],[-0.5,2.75]],"o":[[-2.482,-0.388],[4.63,7.835],[0.5,-2.75]],"v":[[-268.375,-54.75],[-274.375,-49.875],[-262.5,-49.25]],"c":true}]}],"ix":2},"nm":"Path 1","mn":"ADBE Vector Shape - Group","hd":false},{"ty":"st","c":{"a":0,"k":[0,0.188235294118,0.301960784314,1],"ix":3},"o":{"a":0,"k":100,"ix":4},"w":{"a":0,"k":0,"ix":5},"lc":1,"lj":1,"ml":4,"bm":0,"nm":"Stroke 1","mn":"ADBE Vector Graphic - Stroke","hd":false},{"ty":"fl","c":{"a":0,"k":[0,0.188235294118,0.301960784314,1],"ix":4},"o":{"a":0,"k":100,"ix":5},"r":1,"bm":0,"nm":"Fill 1","mn":"ADBE Vector Graphic - Fill","hd":false},{"ty":"tr","p":{"a":0,"k":[0,0],"ix":2},"a":{"a":0,"k":[0,0],"ix":1},"s":{"a":0,"k":[100,100],"ix":3},"r":{"a":0,"k":0,"ix":6},"o":{"a":0,"k":100,"ix":7},"sk":{"a":0,"k":0,"ix":4},"sa":{"a":0,"k":0,"ix":5},"nm":"Transform"}],"nm":"Shape 1","np":3,"cix":2,"bm":0,"ix":1,"mn":"ADBE Vector Group","hd":false}],"ip":16,"op":18,"st":-21,"bm":0},{"ddd":0,"ind":4,"ty":4,"nm":"Splash_2_Down","sr":1,"ks":{"o":{"a":0,"k":100,"ix":11},"r":{"a":0,"k":0,"ix":10},"p":{"a":0,"k":[296.694,315.812,0],"ix":2,"l":2},"a":{"a":0,"k":[0,0,0],"ix":1,"l":2},"s":{"a":0,"k":[59.13,59.13,100],"ix":6,"l":2}},"ao":0,"shapes":[{"ty":"gr","it":[{"ind":0,"ty":"sh","ix":1,"ks":{"a":1,"k":[{"i":{"x":0.833,"y":0.833},"o":{"x":0.167,"y":0.167},"t":16,"s":[{"i":[[3.75,0],[-0.25,-13.5],[0,0],[0.5,10.25]],"o":[[-3.75,0],[0.25,13.5],[0,0],[-0.514,-10.538]],"v":[[-270.25,-17.75],[-278.5,-7.75],[-268,4.5],[-259.75,-4.5]],"c":true}]},{"i":{"x":0.833,"y":0.833},"o":{"x":0.167,"y":0.167},"t":17,"s":[{"i":[[3.75,0],[0.557,-7.358],[0,0],[0.539,10.248]],"o":[[-3.75,0],[-0.625,8.25],[0,0],[-0.375,-7.125]],"v":[[-270.25,-20.25],[-278.625,-12.875],[-268.5,-4.25],[-260.625,-12.75]],"c":true}]},{"i":{"x":0.833,"y":0.833},"o":{"x":0.167,"y":0.167},"t":18,"s":[{"i":[[3.75,0],[-0.125,-3],[0,0],[0.563,5.345]],"o":[[-3.75,0],[0.177,4.248],[0,0],[-0.5,-4.75]],"v":[[-270.25,-20.25],[-278.25,-16.25],[-268.625,-10.75],[-260.75,-15.625]],"c":true}]},{"t":19,"s":[{"i":[[2.5,-0.188],[0.28,-2.99],[0,0],[0.188,2.875]],"o":[[-3.74,0.28],[-0.188,2],[0,0],[-0.094,-1.447]],"v":[[-268.312,-20.625],[-273.688,-16.188],[-269.312,-14.125],[-265.75,-17.75]],"c":true}]}],"ix":2},"nm":"Path 1","mn":"ADBE Vector Shape - Group","hd":false},{"ty":"st","c":{"a":0,"k":[0,0.188235294118,0.301960784314,1],"ix":3},"o":{"a":0,"k":100,"ix":4},"w":{"a":0,"k":0,"ix":5},"lc":1,"lj":1,"ml":4,"bm":0,"nm":"Stroke 1","mn":"ADBE Vector Graphic - Stroke","hd":false},{"ty":"fl","c":{"a":0,"k":[0,0.188235294118,0.301960784314,1],"ix":4},"o":{"a":0,"k":100,"ix":5},"r":1,"bm":0,"nm":"Fill 1","mn":"ADBE Vector Graphic - Fill","hd":false},{"ty":"tr","p":{"a":0,"k":[0,0],"ix":2},"a":{"a":0,"k":[0,0],"ix":1},"s":{"a":0,"k":[100,100],"ix":3},"r":{"a":0,"k":0,"ix":6},"o":{"a":0,"k":100,"ix":7},"sk":{"a":0,"k":0,"ix":4},"sa":{"a":0,"k":0,"ix":5},"nm":"Transform"}],"nm":"Shape 1","np":3,"cix":2,"bm":0,"ix":1,"mn":"ADBE Vector Group","hd":false}],"ip":16,"op":20,"st":-21,"bm":0},{"ddd":0,"ind":5,"ty":4,"nm":"Splash_1_Down","sr":1,"ks":{"o":{"a":0,"k":100,"ix":11},"r":{"a":0,"k":0,"ix":10},"p":{"a":0,"k":[296.694,315.812,0],"ix":2,"l":2},"a":{"a":0,"k":[0,0,0],"ix":1,"l":2},"s":{"a":0,"k":[59.13,59.13,100],"ix":6,"l":2}},"ao":0,"shapes":[{"ty":"gr","it":[{"ind":0,"ty":"sh","ix":1,"ks":{"a":1,"k":[{"i":{"x":0.833,"y":0.833},"o":{"x":0.167,"y":0.167},"t":13,"s":[{"i":[[0,0],[8.595,-27.911],[0,0],[-14,-0.5],[0.5,5.75],[-0.226,16.047]],"o":[[0,0],[-4.063,13.195],[0,0],[14,0.5],[-0.5,-5.75],[0.222,-15.729]],"v":[[-246,-128.048],[-265.904,-93.664],[-269.318,-69.822],[-261.068,-47.822],[-252.568,-68.072],[-255.818,-95.572]],"c":true}]},{"i":{"x":0.833,"y":0.833},"o":{"x":0.167,"y":0.167},"t":14,"s":[{"i":[[0,0],[8.595,-27.911],[0,0],[-14,-0.5],[0.5,5.75],[-0.226,16.047]],"o":[[0,0],[-4.063,13.195],[0,0],[14,0.5],[-0.5,-5.75],[0.222,-15.729]],"v":[[-252.507,-65.377],[-272.411,-30.993],[-275.825,-7.151],[-267.575,14.849],[-259.075,-5.401],[-262.325,-32.901]],"c":true}]},{"t":15,"s":[{"i":[[0,0],[-4.75,-16],[0,0],[-14,-0.5],[0.5,5.75],[-5.459,15.092]],"o":[[0,0],[3.929,13.236],[0,0],[14,0.5],[-0.5,-5.75],[4.25,-11.75]],"v":[[-270.25,-47.75],[-275.25,-34.25],[-275.75,-11.5],[-270.5,11.25],[-263.25,-9],[-263.5,-37]],"c":true}]}],"ix":2},"nm":"Path 1","mn":"ADBE Vector Shape - Group","hd":false},{"ty":"st","c":{"a":0,"k":[0,0.188235294118,0.301960784314,1],"ix":3},"o":{"a":0,"k":100,"ix":4},"w":{"a":0,"k":0,"ix":5},"lc":1,"lj":1,"ml":4,"bm":0,"nm":"Stroke 1","mn":"ADBE Vector Graphic - Stroke","hd":false},{"ty":"fl","c":{"a":0,"k":[0,0.188235294118,0.301960784314,1],"ix":4},"o":{"a":0,"k":100,"ix":5},"r":1,"bm":0,"nm":"Fill 1","mn":"ADBE Vector Graphic - Fill","hd":false},{"ty":"tr","p":{"a":0,"k":[0,0],"ix":2},"a":{"a":0,"k":[0,0],"ix":1},"s":{"a":0,"k":[100,100],"ix":3},"r":{"a":0,"k":0,"ix":6},"o":{"a":0,"k":100,"ix":7},"sk":{"a":0,"k":0,"ix":4},"sa":{"a":0,"k":0,"ix":5},"nm":"Transform"}],"nm":"Shape 1","np":3,"cix":2,"bm":0,"ix":1,"mn":"ADBE Vector Group","hd":false}],"ip":13,"op":16,"st":-21,"bm":0},{"ddd":0,"ind":6,"ty":4,"nm":"Splash_1_Up","sr":1,"ks":{"o":{"a":0,"k":100,"ix":11},"r":{"a":0,"k":0,"ix":10},"p":{"a":0,"k":[296.694,190.262,0],"ix":2,"l":2},"a":{"a":0,"k":[0,0,0],"ix":1,"l":2},"s":{"a":0,"k":[59.13,59.13,100],"ix":6,"l":2}},"ao":0,"shapes":[{"ty":"gr","it":[{"ind":0,"ty":"sh","ix":1,"ks":{"a":1,"k":[{"i":{"x":0.833,"y":0.833},"o":{"x":0.167,"y":0.167},"t":13,"s":[{"i":[[0,0],[3.801,-24.144],[0,0],[-14,-0.5],[0.5,5.75],[-0.226,16.047]],"o":[[0,0],[-2.147,13.639],[0,0],[14,0.5],[-0.5,-5.75],[0.222,-15.729]],"v":[[-251.479,-66.747],[-262.822,-52.226],[-266.236,-28.384],[-257.986,-6.384],[-249.486,-26.634],[-252.736,-54.134]],"c":true}]},{"i":{"x":0.833,"y":0.833},"o":{"x":0.167,"y":0.167},"t":14,"s":[{"i":[[0,0],[3.801,-24.144],[0,0],[-14,-0.5],[0.5,5.75],[-0.226,16.047]],"o":[[0,0],[-2.147,13.639],[0,0],[14,0.5],[-0.5,-5.75],[0.222,-15.729]],"v":[[-261.411,-36.61],[-275.836,-12.842],[-279.25,11],[-271,33],[-262.5,12.75],[-265.75,-14.75]],"c":true}]},{"t":15,"s":[{"i":[[0,0],[-4.75,-16],[0,0],[-14,-0.5],[0.5,5.75],[-5.459,15.092]],"o":[[0,0],[3.929,13.236],[0,0],[14,0.5],[-0.5,-5.75],[4.25,-11.75]],"v":[[-270.25,-47.75],[-275.25,-34.25],[-275.75,-11.5],[-270.5,11.25],[-263.25,-9],[-263.5,-37]],"c":true}]}],"ix":2},"nm":"Path 1","mn":"ADBE Vector Shape - Group","hd":false},{"ty":"st","c":{"a":0,"k":[0,0.188235294118,0.301960784314,1],"ix":3},"o":{"a":0,"k":100,"ix":4},"w":{"a":0,"k":0,"ix":5},"lc":1,"lj":1,"ml":4,"bm":0,"nm":"Stroke 1","mn":"ADBE Vector Graphic - Stroke","hd":false},{"ty":"fl","c":{"a":0,"k":[0,0.188235294118,0.301960784314,1],"ix":4},"o":{"a":0,"k":100,"ix":5},"r":1,"bm":0,"nm":"Fill 1","mn":"ADBE Vector Graphic - Fill","hd":false},{"ty":"tr","p":{"a":0,"k":[0,0],"ix":2},"a":{"a":0,"k":[0,0],"ix":1},"s":{"a":0,"k":[100,100],"ix":3},"r":{"a":0,"k":0,"ix":6},"o":{"a":0,"k":100,"ix":7},"sk":{"a":0,"k":0,"ix":4},"sa":{"a":0,"k":0,"ix":5},"nm":"Transform"}],"nm":"Shape 1","np":3,"cix":2,"bm":0,"ix":1,"mn":"ADBE Vector Group","hd":false}],"ip":13,"op":16,"st":-21,"bm":0},{"ddd":0,"ind":7,"ty":4,"nm":"Splash_2_Up","sr":1,"ks":{"o":{"a":0,"k":100,"ix":11},"r":{"a":0,"k":0,"ix":10},"p":{"a":0,"k":[296.694,190.262,0],"ix":2,"l":2},"a":{"a":0,"k":[0,0,0],"ix":1,"l":2},"s":{"a":0,"k":[59.13,59.13,100],"ix":6,"l":2}},"ao":0,"shapes":[{"ty":"gr","it":[{"ind":0,"ty":"sh","ix":1,"ks":{"a":1,"k":[{"i":{"x":0.833,"y":0.833},"o":{"x":0.167,"y":0.167},"t":16,"s":[{"i":[[3.75,0],[-0.25,-13.5],[0,0],[0.5,10.25]],"o":[[-3.75,0],[0.25,13.5],[0,0],[-0.514,-10.538]],"v":[[-270.25,-17.75],[-278.5,-7.75],[-268,4.5],[-259.75,-4.5]],"c":true}]},{"i":{"x":0.833,"y":0.833},"o":{"x":0.167,"y":0.167},"t":17,"s":[{"i":[[3.75,0],[0.557,-7.358],[0,0],[0.539,10.248]],"o":[[-3.75,0],[-0.625,8.25],[0,0],[-0.375,-7.125]],"v":[[-270.25,-20.25],[-278.625,-12.875],[-268.5,-4.25],[-260.625,-12.75]],"c":true}]},{"i":{"x":0.833,"y":0.833},"o":{"x":0.167,"y":0.167},"t":18,"s":[{"i":[[3.75,0],[-0.125,-3],[0,0],[0.563,5.345]],"o":[[-3.75,0],[0.177,4.248],[0,0],[-0.5,-4.75]],"v":[[-270.25,-20.25],[-278.25,-16.25],[-268.625,-10.75],[-260.75,-15.625]],"c":true}]},{"t":19,"s":[{"i":[[2.5,-0.188],[0.28,-2.99],[0,0],[0.188,2.875]],"o":[[-3.74,0.28],[-0.188,2],[0,0],[-0.094,-1.447]],"v":[[-268.312,-20.625],[-273.688,-16.188],[-269.312,-14.125],[-265.75,-17.75]],"c":true}]}],"ix":2},"nm":"Path 1","mn":"ADBE Vector Shape - Group","hd":false},{"ty":"st","c":{"a":0,"k":[0,0.188235294118,0.301960784314,1],"ix":3},"o":{"a":0,"k":100,"ix":4},"w":{"a":0,"k":0,"ix":5},"lc":1,"lj":1,"ml":4,"bm":0,"nm":"Stroke 1","mn":"ADBE Vector Graphic - Stroke","hd":false},{"ty":"fl","c":{"a":0,"k":[0,0.188235294118,0.301960784314,1],"ix":4},"o":{"a":0,"k":100,"ix":5},"r":1,"bm":0,"nm":"Fill 1","mn":"ADBE Vector Graphic - Fill","hd":false},{"ty":"tr","p":{"a":0,"k":[0,0],"ix":2},"a":{"a":0,"k":[0,0],"ix":1},"s":{"a":0,"k":[100,100],"ix":3},"r":{"a":0,"k":0,"ix":6},"o":{"a":0,"k":100,"ix":7},"sk":{"a":0,"k":0,"ix":4},"sa":{"a":0,"k":0,"ix":5},"nm":"Transform"}],"nm":"Shape 1","np":3,"cix":2,"bm":0,"ix":1,"mn":"ADBE Vector Group","hd":false}],"ip":16,"op":20,"st":-21,"bm":0},{"ddd":0,"ind":8,"ty":4,"nm":"Splash_3_Up","sr":1,"ks":{"o":{"a":0,"k":100,"ix":11},"r":{"a":0,"k":0,"ix":10},"p":{"a":0,"k":[296.694,190.262,0],"ix":2,"l":2},"a":{"a":0,"k":[0,0,0],"ix":1,"l":2},"s":{"a":0,"k":[59.13,59.13,100],"ix":6,"l":2}},"ao":0,"shapes":[{"ty":"gr","it":[{"ind":0,"ty":"sh","ix":1,"ks":{"a":1,"k":[{"i":{"x":0.833,"y":0.833},"o":{"x":0.167,"y":0.167},"t":16,"s":[{"i":[[8.823,-0.882],[-6.125,-10],[-0.5,2.75]],"o":[[-2.5,0.25],[6.125,10],[0.5,-2.75]],"v":[[-271.125,-52.875],[-274.875,-42.125],[-263.75,-43]],"c":true}]},{"t":17,"s":[{"i":[[4,0.625],[-1.625,-2.75],[-0.5,2.75]],"o":[[-2.482,-0.388],[4.63,7.835],[0.5,-2.75]],"v":[[-268.375,-54.75],[-274.375,-49.875],[-262.5,-49.25]],"c":true}]}],"ix":2},"nm":"Path 1","mn":"ADBE Vector Shape - Group","hd":false},{"ty":"st","c":{"a":0,"k":[0,0.188235294118,0.301960784314,1],"ix":3},"o":{"a":0,"k":100,"ix":4},"w":{"a":0,"k":0,"ix":5},"lc":1,"lj":1,"ml":4,"bm":0,"nm":"Stroke 1","mn":"ADBE Vector Graphic - Stroke","hd":false},{"ty":"fl","c":{"a":0,"k":[0,0.188235294118,0.301960784314,1],"ix":4},"o":{"a":0,"k":100,"ix":5},"r":1,"bm":0,"nm":"Fill 1","mn":"ADBE Vector Graphic - Fill","hd":false},{"ty":"tr","p":{"a":0,"k":[0,0],"ix":2},"a":{"a":0,"k":[0,0],"ix":1},"s":{"a":0,"k":[100,100],"ix":3},"r":{"a":0,"k":0,"ix":6},"o":{"a":0,"k":100,"ix":7},"sk":{"a":0,"k":0,"ix":4},"sa":{"a":0,"k":0,"ix":5},"nm":"Transform"}],"nm":"Shape 1","np":3,"cix":2,"bm":0,"ix":1,"mn":"ADBE Vector Group","hd":false}],"ip":16,"op":18,"st":-21,"bm":0},{"ddd":0,"ind":9,"ty":4,"nm":"Splash_4_Up","sr":1,"ks":{"o":{"a":0,"k":100,"ix":11},"r":{"a":0,"k":0,"ix":10},"p":{"a":0,"k":[298.719,190.262,0],"ix":2,"l":2},"a":{"a":0,"k":[0,0,0],"ix":1,"l":2},"s":{"a":0,"k":[59.13,59.13,100],"ix":6,"l":2}},"ao":0,"shapes":[{"ty":"gr","it":[{"ind":0,"ty":"sh","ix":1,"ks":{"a":1,"k":[{"i":{"x":0.833,"y":0.833},"o":{"x":0.167,"y":0.167},"t":13,"s":[{"i":[[0,0],[-5.823,-14.538],[-0.443,-3.634],[-1.232,7.916]],"o":[[0,0],[3.535,8.825],[0.712,5.849],[3.489,-22.414]],"v":[[-256.709,73.401],[-260.904,87.654],[-248.647,101.579],[-250.01,92.791]],"c":true}]},{"i":{"x":0.833,"y":0.833},"o":{"x":0.167,"y":0.167},"t":14,"s":[{"i":[[0,0],[-5.823,-14.538],[-0.443,-3.634],[-1.232,7.916]],"o":[[0,0],[3.535,8.825],[0.712,5.849],[3.489,-22.414]],"v":[[-272.805,39.497],[-277,53.75],[-264.743,67.675],[-266.106,58.887]],"c":true}]},{"i":{"x":0.833,"y":0.833},"o":{"x":0.167,"y":0.167},"t":15,"s":[{"i":[[0,0],[-1.707,-10.054],[0,0],[0.562,9.375]],"o":[[0,0],[1.125,6.625],[0,0],[-0.593,-9.888]],"v":[[-269.812,33.125],[-275.5,44],[-267.75,49],[-263.688,40.75]],"c":true}]},{"t":16,"s":[{"i":[[0,0],[-0.375,-5.625],[0,0],[0.037,3.125]],"o":[[0,0],[0.447,6.705],[0,0],[-0.062,-5.25]],"v":[[-269.812,33.125],[-273.75,38.25],[-269.5,40.875],[-266.312,36.75]],"c":true}]}],"ix":2},"nm":"Path 1","mn":"ADBE Vector Shape - Group","hd":false},{"ty":"st","c":{"a":0,"k":[0,0.188235294118,0.301960784314,1],"ix":3},"o":{"a":0,"k":100,"ix":4},"w":{"a":0,"k":0,"ix":5},"lc":1,"lj":1,"ml":4,"bm":0,"nm":"Stroke 1","mn":"ADBE Vector Graphic - Stroke","hd":false},{"ty":"fl","c":{"a":0,"k":[0,0.188235294118,0.301960784314,1],"ix":4},"o":{"a":0,"k":100,"ix":5},"r":1,"bm":0,"nm":"Fill 1","mn":"ADBE Vector Graphic - Fill","hd":false},{"ty":"tr","p":{"a":0,"k":[0,0],"ix":2},"a":{"a":0,"k":[0,0],"ix":1},"s":{"a":0,"k":[100,100],"ix":3},"r":{"a":0,"k":0,"ix":6},"o":{"a":0,"k":100,"ix":7},"sk":{"a":0,"k":0,"ix":4},"sa":{"a":0,"k":0,"ix":5},"nm":"Transform"}],"nm":"Shape 1","np":3,"cix":2,"bm":0,"ix":1,"mn":"ADBE Vector Group","hd":false}],"ip":13,"op":17,"st":-21,"bm":0},{"ddd":0,"ind":10,"ty":4,"nm":"Mask_2_Down","sr":1,"ks":{"o":{"a":0,"k":100,"ix":11},"r":{"a":0,"k":0,"ix":10},"p":{"a":0,"k":[210.36,353.68,0],"ix":2,"l":2},"a":{"a":0,"k":[0,0,0],"ix":1,"l":2},"s":{"a":0,"k":[81,81,100],"ix":6,"l":2}},"ao":0,"shapes":[{"ty":"gr","it":[{"ind":0,"ty":"sh","ix":1,"ks":{"a":1,"k":[{"i":{"x":0.833,"y":0.833},"o":{"x":0.167,"y":0.167},"t":14,"s":[{"i":[[0,0],[0,0],[6.25,-20.25],[-2.5,4],[-22.25,-0.25]],"o":[[0,0],[0,0],[-5.091,16.495],[2.5,-4],[22.25,0.25]],"v":[[-81.375,-123.875],[-94.25,-96.125],[-85.5,-86],[-82.25,-84.5],[-50,-101]],"c":true}]},{"i":{"x":0.667,"y":1},"o":{"x":0.167,"y":0.167},"t":15,"s":[{"i":[[0,0],[0,0],[-4.875,-5.5],[-1.25,1.75],[-22.25,-0.25]],"o":[[0,0],[0,0],[3.804,4.292],[2.742,-3.838],[22.25,0.25]],"v":[[-103.125,-128.875],[-102.5,-81],[-92.125,-92.5],[-84,-98],[-53.5,-101.625]],"c":true}]},{"t":22,"s":[{"i":[[0,0],[0,0],[-7.35,0],[-2.25,0],[-22.25,-0.25]],"o":[[0,0],[0,0],[4.875,0],[4.717,0],[22.25,0.25]],"v":[[-103.125,-128.875],[-116.875,-100.375],[-92.25,-101.75],[-84,-101.25],[-53.5,-101.625]],"c":true}]}],"ix":2},"nm":"Path 1","mn":"ADBE Vector Shape - Group","hd":false},{"ty":"st","c":{"a":0,"k":[0,0.188235294118,0.301960784314,1],"ix":3},"o":{"a":0,"k":100,"ix":4},"w":{"a":0,"k":0,"ix":5},"lc":1,"lj":1,"ml":4,"bm":0,"nm":"Stroke 1","mn":"ADBE Vector Graphic - Stroke","hd":false},{"ty":"fl","c":{"a":0,"k":[0,0.188235294118,0.301960784314,1],"ix":4},"o":{"a":0,"k":100,"ix":5},"r":1,"bm":0,"nm":"Fill 1","mn":"ADBE Vector Graphic - Fill","hd":false},{"ty":"tr","p":{"a":0,"k":[0,0],"ix":2},"a":{"a":0,"k":[0,0],"ix":1},"s":{"a":0,"k":[100,100],"ix":3},"r":{"a":0,"k":0,"ix":6},"o":{"a":0,"k":100,"ix":7},"sk":{"a":0,"k":0,"ix":4},"sa":{"a":0,"k":0,"ix":5},"nm":"Transform"}],"nm":"Shape 1","np":3,"cix":2,"bm":0,"ix":1,"mn":"ADBE Vector Group","hd":false}],"ip":13,"op":23,"st":0,"bm":0},{"ddd":0,"ind":11,"ty":4,"nm":"Mask_1_Down","sr":1,"ks":{"o":{"a":0,"k":100,"ix":11},"r":{"a":0,"k":0,"ix":10},"p":{"a":0,"k":[210.36,373.93,0],"ix":2,"l":2},"a":{"a":0,"k":[0,0,0],"ix":1,"l":2},"s":{"a":0,"k":[81,81,100],"ix":6,"l":2}},"ao":0,"shapes":[{"ty":"gr","it":[{"ind":0,"ty":"sh","ix":1,"ks":{"a":1,"k":[{"i":{"x":0.833,"y":0.833},"o":{"x":0.167,"y":0.167},"t":13,"s":[{"i":[[0.938,0],[-3.654,-9.501],[0,0],[0,0],[0,0],[14,-0.5],[4.168,10.58]],"o":[[-0.938,0],[5,13],[0,0],[0,0],[0,0],[-14,0.5],[-3.25,-8.25]],"v":[[-84.625,-61],[-80.75,-45.125],[-88,-46.875],[-90.75,-24.5],[-59.75,-20.5],[-50.75,-32.75],[-79.5,-49.75]],"c":true}]},{"i":{"x":0.833,"y":0.833},"o":{"x":0.167,"y":0.167},"t":14,"s":[{"i":[[0.938,0],[-3.654,-9.501],[0,0],[0,0],[0,0],[14,-0.5],[4.168,10.58]],"o":[[-0.938,0],[5,13],[0,0],[0,0],[0,0],[-14,0.5],[-3.25,-8.25]],"v":[[-84.625,-61],[-80.75,-45.125],[-88,-46.875],[-90.75,-15],[-60.25,-11.5],[-50.75,-32.75],[-79.5,-49.75]],"c":true}]},{"i":{"x":0.833,"y":0.833},"o":{"x":0.167,"y":0.167},"t":15,"s":[{"i":[[3.125,0.375],[4.875,3.938],[0,0],[0,0],[0,0],[14,-0.5],[11.369,0.258]],"o":[[-6.093,-0.731],[-10.835,-8.752],[0,0],[0,0],[0,0],[-14,0.5],[-22,-0.5]],"v":[[-86.75,-27.625],[-98.188,-22.875],[-117.125,-21.125],[-102.25,19],[-71.75,22.5],[-62.25,1.25],[-63,-13.375]],"c":true}]},{"i":{"x":0.667,"y":1},"o":{"x":0.167,"y":0.167},"t":17,"s":[{"i":[[3.125,0.375],[4.875,3.938],[0,0],[0,0],[0,0],[14,-0.5],[11.369,0.258]],"o":[[-6.093,-0.731],[-10.835,-8.752],[0,0],[0,0],[0,0],[-14,0.5],[-22,-0.5]],"v":[[-87.118,-38.495],[-98.211,-34.851],[-117.171,-39.917],[-111.658,4.813],[-71.658,4.813],[-48.223,1.063],[-47.132,-4.641]],"c":true}]},{"t":22,"s":[{"i":[[3.125,0.375],[4.875,3.938],[0,0],[0,0],[0,0],[14,-0.5],[11.369,0.258]],"o":[[-6.093,-0.731],[-10.835,-8.752],[0,0],[0,0],[0,0],[-14,0.5],[-22,-0.5]],"v":[[-87.75,-57.125],[-98.25,-55.375],[-117.25,-72.125],[-102,-29],[-71.5,-25.5],[-56.75,-46.75],[-62,-58.875]],"c":true}]}],"ix":2},"nm":"Path 1","mn":"ADBE Vector Shape - Group","hd":false},{"ty":"st","c":{"a":0,"k":[0,0.188235294118,0.301960784314,1],"ix":3},"o":{"a":0,"k":100,"ix":4},"w":{"a":0,"k":0,"ix":5},"lc":1,"lj":1,"ml":4,"bm":0,"nm":"Stroke 1","mn":"ADBE Vector Graphic - Stroke","hd":false},{"ty":"fl","c":{"a":0,"k":[0,0.188235294118,0.301960784314,1],"ix":4},"o":{"a":0,"k":100,"ix":5},"r":1,"bm":0,"nm":"Fill 1","mn":"ADBE Vector Graphic - Fill","hd":false},{"ty":"tr","p":{"a":0,"k":[0,0],"ix":2},"a":{"a":0,"k":[0,0],"ix":1},"s":{"a":0,"k":[100,100],"ix":3},"r":{"a":0,"k":0,"ix":6},"o":{"a":0,"k":100,"ix":7},"sk":{"a":0,"k":0,"ix":4},"sa":{"a":0,"k":0,"ix":5},"nm":"Transform"}],"nm":"Shape 1","np":3,"cix":2,"bm":0,"ix":1,"mn":"ADBE Vector Group","hd":false}],"ip":13,"op":23,"st":0,"bm":0},{"ddd":0,"ind":12,"ty":4,"nm":"Mask_2_Up","sr":1,"ks":{"o":{"a":0,"k":100,"ix":11},"r":{"a":0,"k":0,"ix":10},"p":{"a":0,"k":[204.69,263.77,0],"ix":2,"l":2},"a":{"a":0,"k":[0,0,0],"ix":1,"l":2},"s":{"a":0,"k":[81,81,100],"ix":6,"l":2}},"ao":0,"shapes":[{"ty":"gr","it":[{"ind":0,"ty":"sh","ix":1,"ks":{"a":1,"k":[{"i":{"x":0.833,"y":0.833},"o":{"x":0.167,"y":0.167},"t":13,"s":[{"i":[[0.938,0],[-3.654,-9.501],[0,0],[0,0],[0,0],[14,-0.5],[2.034,11.188]],"o":[[-0.938,0],[5,13],[0,0],[0,0],[0,0],[-14,0.5],[-1.5,-8.25]],"v":[[-75.25,-53.875],[-73.75,-38.125],[-88,-46.875],[-90.75,-15],[-60.25,-11.5],[-50.75,-32.75],[-70.75,-34.5]],"c":true}]},{"i":{"x":0.833,"y":0.833},"o":{"x":0.167,"y":0.167},"t":14,"s":[{"i":[[0.938,0],[-3.654,-9.501],[0,0],[0,0],[0,0],[14,-0.5],[4.168,10.58]],"o":[[-0.938,0],[5,13],[0,0],[0,0],[0,0],[-14,0.5],[-3.25,-8.25]],"v":[[-84.625,-61],[-80.75,-45.125],[-88,-46.875],[-90.75,-15],[-60.25,-11.5],[-50.75,-32.75],[-79.5,-49.75]],"c":true}]},{"i":{"x":0.833,"y":0.833},"o":{"x":0.167,"y":0.167},"t":15,"s":[{"i":[[3.125,0.375],[4.875,3.938],[0,0],[0,0],[0,0],[14,-0.5],[11.369,0.258]],"o":[[-6.093,-0.731],[-10.835,-8.752],[0,0],[0,0],[0,0],[-14,0.5],[-22,-0.5]],"v":[[-76.75,-46.875],[-88.188,-42.125],[-107.125,-40.375],[-92.25,-0.25],[-61.75,3.25],[-52.25,-18],[-53,-32.625]],"c":true}]},{"i":{"x":0.667,"y":1},"o":{"x":0.167,"y":0.167},"t":16,"s":[{"i":[[3.125,0.375],[4.875,3.938],[0,0],[0,0],[0,0],[14,-0.5],[11.369,0.258]],"o":[[-6.093,-0.731],[-10.835,-8.752],[0,0],[0,0],[0,0],[-14,0.5],[-22,-0.5]],"v":[[-76.75,-46.875],[-88.188,-42.125],[-107.125,-40.375],[-92.25,-0.25],[-61.75,3.25],[-52.25,-18],[-53,-32.625]],"c":true}]},{"t":22,"s":[{"i":[[3.125,0.375],[4.875,3.938],[0,0],[0,0],[0,0],[14,-0.5],[11.369,0.258]],"o":[[-6.093,-0.731],[-10.835,-8.752],[0,0],[0,0],[0,0],[-14,0.5],[-22,-0.5]],"v":[[-76.75,-31.375],[-99.188,-31.875],[-107.125,-40.375],[-92.25,-0.25],[-61.75,3.25],[-52.25,-18],[-53,-30.375]],"c":true}]}],"ix":2},"nm":"Path 1","mn":"ADBE Vector Shape - Group","hd":false},{"ty":"st","c":{"a":0,"k":[0,0.188235294118,0.301960784314,1],"ix":3},"o":{"a":0,"k":100,"ix":4},"w":{"a":0,"k":0,"ix":5},"lc":1,"lj":1,"ml":4,"bm":0,"nm":"Stroke 1","mn":"ADBE Vector Graphic - Stroke","hd":false},{"ty":"fl","c":{"a":0,"k":[0,0.188235294118,0.301960784314,1],"ix":4},"o":{"a":0,"k":100,"ix":5},"r":1,"bm":0,"nm":"Fill 1","mn":"ADBE Vector Graphic - Fill","hd":false},{"ty":"tr","p":{"a":0,"k":[0,0],"ix":2},"a":{"a":0,"k":[0,0],"ix":1},"s":{"a":0,"k":[100,100],"ix":3},"r":{"a":0,"k":0,"ix":6},"o":{"a":0,"k":100,"ix":7},"sk":{"a":0,"k":0,"ix":4},"sa":{"a":0,"k":0,"ix":5},"nm":"Transform"}],"nm":"Shape 1","np":3,"cix":2,"bm":0,"ix":1,"mn":"ADBE Vector Group","hd":false}],"ip":13,"op":23,"st":0,"bm":0},{"ddd":0,"ind":13,"ty":4,"nm":"Mask_1_Up","sr":1,"ks":{"o":{"a":0,"k":100,"ix":11},"r":{"a":0,"k":0,"ix":10},"p":{"a":0,"k":[204.69,243.52,0],"ix":2,"l":2},"a":{"a":0,"k":[0,0,0],"ix":1,"l":2},"s":{"a":0,"k":[81,81,100],"ix":6,"l":2}},"ao":0,"shapes":[{"ty":"gr","it":[{"ind":0,"ty":"sh","ix":1,"ks":{"a":1,"k":[{"i":{"x":0.833,"y":0.833},"o":{"x":0.167,"y":0.167},"t":13,"s":[{"i":[[0,0],[0,0],[6.25,-20.25],[-2.5,4],[-22.25,-0.25]],"o":[[0,0],[0,0],[-5.091,16.495],[2.5,-4],[22.25,0.25]],"v":[[-81.875,-113.375],[-89.75,-90.375],[-85.5,-86],[-82.25,-84.5],[-50,-101]],"c":true}]},{"i":{"x":0.833,"y":0.833},"o":{"x":0.167,"y":0.167},"t":14,"s":[{"i":[[0,0],[0,0],[6.25,-20.25],[-2.5,4],[-22.25,-0.25]],"o":[[0,0],[0,0],[-5.091,16.495],[2.5,-4],[22.25,0.25]],"v":[[-81.375,-123.875],[-89.75,-90.375],[-85.5,-86],[-82.25,-84.5],[-50,-101]],"c":true}]},{"i":{"x":0.833,"y":0.833},"o":{"x":0.167,"y":0.167},"t":15,"s":[{"i":[[0,0],[0,0],[-4.875,-5.5],[-1.25,1.75],[-22.25,-0.25]],"o":[[0,0],[0,0],[3.804,4.292],[2.742,-3.838],[22.25,0.25]],"v":[[-96.125,-146.375],[-95.5,-98.5],[-85.125,-110],[-77,-115.5],[-46.5,-119.125]],"c":true}]},{"i":{"x":0.833,"y":0.833},"o":{"x":0.167,"y":0.167},"t":16,"s":[{"i":[[0,0],[0,0],[-4.875,-5.5],[-1.25,1.75],[-22.25,-0.25]],"o":[[0,0],[0,0],[3.804,4.292],[2.742,-3.838],[22.25,0.25]],"v":[[-96.125,-146.375],[-95.5,-98.5],[-85.125,-110],[-77,-115.5],[-44.5,-129.125]],"c":true}]},{"i":{"x":0.667,"y":1},"o":{"x":0.167,"y":0.167},"t":17,"s":[{"i":[[0,0],[0,0],[-4.875,-5.5],[-1.25,1.75],[-22.25,-0.25]],"o":[[0,0],[0,0],[3.804,4.292],[2.742,-3.838],[22.25,0.25]],"v":[[-97.484,-138.953],[-99.681,-92.646],[-85.151,-103.415],[-77,-107.451],[-44.545,-128.071]],"c":true}]},{"t":22,"s":[{"i":[[0,0],[0,0],[-4.875,-5.5],[-1.25,1.75],[-22.25,-0.25]],"o":[[0,0],[0,0],[3.804,4.292],[2.742,-3.838],[22.25,0.25]],"v":[[-102.625,-110.875],[-115.5,-70.5],[-85.25,-78.5],[-77,-77],[-49.5,-112.125]],"c":true}]}],"ix":2},"nm":"Path 1","mn":"ADBE Vector Shape - Group","hd":false},{"ty":"st","c":{"a":0,"k":[0,0.188235294118,0.301960784314,1],"ix":3},"o":{"a":0,"k":100,"ix":4},"w":{"a":0,"k":0,"ix":5},"lc":1,"lj":1,"ml":4,"bm":0,"nm":"Stroke 1","mn":"ADBE Vector Graphic - Stroke","hd":false},{"ty":"fl","c":{"a":0,"k":[0,0.188235294118,0.301960784314,1],"ix":4},"o":{"a":0,"k":100,"ix":5},"r":1,"bm":0,"nm":"Fill 1","mn":"ADBE Vector Graphic - Fill","hd":false},{"ty":"tr","p":{"a":0,"k":[0,0],"ix":2},"a":{"a":0,"k":[0,0],"ix":1},"s":{"a":0,"k":[100,100],"ix":3},"r":{"a":0,"k":0,"ix":6},"o":{"a":0,"k":100,"ix":7},"sk":{"a":0,"k":0,"ix":4},"sa":{"a":0,"k":0,"ix":5},"nm":"Transform"}],"nm":"Shape 1","np":3,"cix":2,"bm":0,"ix":1,"mn":"ADBE Vector Group","hd":false}],"ip":13,"op":23,"st":0,"bm":0},{"ddd":0,"ind":14,"ty":4,"nm":"Mask_2","sr":1,"ks":{"o":{"a":0,"k":100,"ix":11},"r":{"a":0,"k":0,"ix":10},"p":{"a":0,"k":[212.79,263.77,0],"ix":2,"l":2},"a":{"a":0,"k":[0,0,0],"ix":1,"l":2},"s":{"a":0,"k":[81,81,100],"ix":6,"l":2}},"ao":0,"shapes":[{"ty":"gr","it":[{"ind":0,"ty":"sh","ix":1,"ks":{"a":0,"k":{"i":[[0,0],[0,0],[0,0],[0,0],[-17.375,0.25],[0,0]],"o":[[0,0],[0,0],[0,0],[0,0],[17.375,-0.25],[0,0]],"v":[[-116,-1.5],[-121,7],[-116.25,31],[-108.125,24.625],[-92.25,10],[-90.125,1.625]],"c":true},"ix":2},"nm":"Path 1","mn":"ADBE Vector Shape - Group","hd":false},{"ty":"st","c":{"a":0,"k":[0,0.188235294118,0.301960784314,1],"ix":3},"o":{"a":0,"k":100,"ix":4},"w":{"a":0,"k":0,"ix":5},"lc":1,"lj":1,"ml":4,"bm":0,"nm":"Stroke 1","mn":"ADBE Vector Graphic - Stroke","hd":false},{"ty":"fl","c":{"a":0,"k":[0,0.188235294118,0.301960784314,1],"ix":4},"o":{"a":0,"k":100,"ix":5},"r":1,"bm":0,"nm":"Fill 1","mn":"ADBE Vector Graphic - Fill","hd":false},{"ty":"tr","p":{"a":0,"k":[0,0],"ix":2},"a":{"a":0,"k":[0,0],"ix":1},"s":{"a":0,"k":[100,100],"ix":3},"r":{"a":0,"k":0,"ix":6},"o":{"a":0,"k":100,"ix":7},"sk":{"a":0,"k":0,"ix":4},"sa":{"a":0,"k":0,"ix":5},"nm":"Transform"}],"nm":"Shape 4","np":3,"cix":2,"bm":0,"ix":1,"mn":"ADBE Vector Group","hd":false},{"ty":"gr","it":[{"ind":0,"ty":"sh","ix":1,"ks":{"a":0,"k":{"i":[[0,-1.25],[0,0],[0,0],[0,0],[16.125,0.125]],"o":[[0,1.25],[0,0],[0,0],[0,0],[-16.125,-0.125]],"v":[[-108.125,117.25],[-120.5,119.375],[-118.875,132.625],[-97.75,136.375],[-93.75,128.938]],"c":true},"ix":2},"nm":"Path 1","mn":"ADBE Vector Shape - Group","hd":false},{"ty":"st","c":{"a":0,"k":[0,0.188235294118,0.301960784314,1],"ix":3},"o":{"a":0,"k":100,"ix":4},"w":{"a":0,"k":0,"ix":5},"lc":1,"lj":1,"ml":4,"bm":0,"nm":"Stroke 1","mn":"ADBE Vector Graphic - Stroke","hd":false},{"ty":"fl","c":{"a":0,"k":[0,0.188235294118,0.301960784314,1],"ix":4},"o":{"a":0,"k":100,"ix":5},"r":1,"bm":0,"nm":"Fill 1","mn":"ADBE Vector Graphic - Fill","hd":false},{"ty":"tr","p":{"a":0,"k":[0,0],"ix":2},"a":{"a":0,"k":[0,0],"ix":1},"s":{"a":0,"k":[100,100],"ix":3},"r":{"a":0,"k":0,"ix":6},"o":{"a":0,"k":100,"ix":7},"sk":{"a":0,"k":0,"ix":4},"sa":{"a":0,"k":0,"ix":5},"nm":"Transform"}],"nm":"Shape 3","np":3,"cix":2,"bm":0,"ix":2,"mn":"ADBE Vector Group","hd":false},{"ty":"gr","it":[{"ind":0,"ty":"sh","ix":1,"ks":{"a":0,"k":{"i":[[0,0],[0,0],[0,0],[0,10.75],[0,0],[0,0]],"o":[[0,0],[0,0],[0,0],[0,-10.75],[0,0],[0,0]],"v":[[-106.25,-160.25],[-120.875,-155.625],[-123,-148],[-108,-140],[-97.75,-151.25],[-90.875,-156.25]],"c":true},"ix":2},"nm":"Path 1","mn":"ADBE Vector Shape - Group","hd":false},{"ty":"st","c":{"a":0,"k":[0,0.188235294118,0.301960784314,1],"ix":3},"o":{"a":0,"k":100,"ix":4},"w":{"a":0,"k":0,"ix":5},"lc":1,"lj":1,"ml":4,"bm":0,"nm":"Stroke 1","mn":"ADBE Vector Graphic - Stroke","hd":false},{"ty":"fl","c":{"a":0,"k":[0,0.188235294118,0.301960784314,1],"ix":4},"o":{"a":0,"k":100,"ix":5},"r":1,"bm":0,"nm":"Fill 1","mn":"ADBE Vector Graphic - Fill","hd":false},{"ty":"tr","p":{"a":0,"k":[0,0],"ix":2},"a":{"a":0,"k":[0,0],"ix":1},"s":{"a":0,"k":[100,100],"ix":3},"r":{"a":0,"k":0,"ix":6},"o":{"a":0,"k":100,"ix":7},"sk":{"a":0,"k":0,"ix":4},"sa":{"a":0,"k":0,"ix":5},"nm":"Transform"}],"nm":"Shape 2","np":3,"cix":2,"bm":0,"ix":3,"mn":"ADBE Vector Group","hd":false},{"ty":"gr","it":[{"ind":0,"ty":"sh","ix":1,"ks":{"a":0,"k":{"i":[[0,0],[0,0],[0,0],[0,0],[8.375,0]],"o":[[0,0],[0,0],[0,0],[0,0],[-8.375,0]],"v":[[-108.125,-40.875],[-121.5,-38.625],[-119.875,-29.25],[-102,-25.125],[-100.25,-33]],"c":true},"ix":2},"nm":"Path 1","mn":"ADBE Vector Shape - Group","hd":false},{"ty":"st","c":{"a":0,"k":[0,0.188235294118,0.301960784314,1],"ix":3},"o":{"a":0,"k":100,"ix":4},"w":{"a":0,"k":0,"ix":5},"lc":1,"lj":1,"ml":4,"bm":0,"nm":"Stroke 1","mn":"ADBE Vector Graphic - Stroke","hd":false},{"ty":"fl","c":{"a":0,"k":[0,0.188235294118,0.301960784314,1],"ix":4},"o":{"a":0,"k":100,"ix":5},"r":1,"bm":0,"nm":"Fill 1","mn":"ADBE Vector Graphic - Fill","hd":false},{"ty":"tr","p":{"a":0,"k":[0,0],"ix":2},"a":{"a":0,"k":[0,0],"ix":1},"s":{"a":0,"k":[100,100],"ix":3},"r":{"a":0,"k":0,"ix":6},"o":{"a":0,"k":100,"ix":7},"sk":{"a":0,"k":0,"ix":4},"sa":{"a":0,"k":0,"ix":5},"nm":"Transform"}],"nm":"Shape 1","np":3,"cix":2,"bm":0,"ix":4,"mn":"ADBE Vector Group","hd":false}],"ip":15,"op":17,"st":0,"bm":0},{"ddd":0,"ind":15,"ty":4,"nm":"Mask_1","sr":1,"ks":{"o":{"a":0,"k":100,"ix":11},"r":{"a":0,"k":0,"ix":10},"p":{"a":0,"k":[212.79,263.77,0],"ix":2,"l":2},"a":{"a":0,"k":[0,0,0],"ix":1,"l":2},"s":{"a":0,"k":[81,81,100],"ix":6,"l":2}},"ao":0,"hasMask":true,"masksProperties":[{"inv":false,"mode":"s","pt":{"a":1,"k":[{"i":{"x":0.833,"y":0.833},"o":{"x":0.167,"y":0.167},"t":11,"s":[{"i":[[0.375,-4.25],[-0.875,-2.125],[-1.622,0.787],[8.25,1.5]],"o":[[-0.375,4.25],[0.875,2.125],[4.125,-2],[-8.25,-1.5]],"v":[[-18.75,-32.5],[-20.375,-27.125],[-17,-25.5],[-13.25,-40.75]],"c":true}]},{"i":{"x":0.833,"y":0.833},"o":{"x":0.167,"y":0.167},"t":12,"s":[{"i":[[0.375,-4.25],[-0.875,-2.125],[0.068,1.801],[8.367,0.558]],"o":[[-0.375,4.25],[0.875,2.125],[-0.25,-6.625],[-3.75,-0.25]],"v":[[-47.125,-47.5],[-46.25,-40.5],[-42.375,-40.75],[-42.25,-59.125]],"c":true}]},{"t":13,"s":[{"i":[[-0.758,-13.984],[-1.422,-1.805],[0.664,1.676],[11.25,0.5]],"o":[[1.125,20.75],[3.25,4.125],[-13.875,-35],[-3.755,-0.167]],"v":[[-106.375,-75],[-93.5,-40.5],[-82.875,-38.5],[-90.5,-96.25]],"c":true}]}],"ix":1},"o":{"a":0,"k":100,"ix":3},"x":{"a":0,"k":0,"ix":4},"nm":"Mask 1"},{"inv":false,"mode":"s","pt":{"a":1,"k":[{"i":{"x":0.833,"y":0.833},"o":{"x":0.167,"y":0.167},"t":11,"s":[{"i":[[1,-4.25],[-2.5,-1.75],[1.344,1.202],[6.501,2.167]],"o":[[-0.977,4.153],[1.883,1.318],[-7.125,-6.375],[-3.75,-1.25]],"v":[[-20.625,7.625],[-14,16.375],[-9.75,15.75],[-14.75,0.125]],"c":true}]},{"i":{"x":0.833,"y":0.833},"o":{"x":0.167,"y":0.167},"t":12,"s":[{"i":[[0.375,-4.25],[-0.875,-2.125],[0.068,1.801],[8.367,0.558]],"o":[[-0.375,4.25],[0.875,2.125],[-0.25,-6.625],[-3.75,-0.25]],"v":[[-62.125,25],[-61.25,32],[-57.375,31.75],[-57.25,13.375]],"c":true}]},{"t":13,"s":[{"i":[[-0.758,-13.984],[-1.422,-1.805],[0.794,1.618],[11.25,0.5]],"o":[[1.125,20.75],[3.25,4.125],[-20.125,-41],[-3.755,-0.167]],"v":[[-106.375,35],[-93.5,69.5],[-82.875,71.5],[-85.5,13.75]],"c":true}]}],"ix":1},"o":{"a":0,"k":100,"ix":3},"x":{"a":0,"k":0,"ix":4},"nm":"Mask 2"}],"shapes":[{"ty":"gr","it":[{"ind":0,"ty":"sh","ix":1,"ks":{"a":1,"k":[{"i":{"x":0.833,"y":0.833},"o":{"x":0.167,"y":0.167},"t":10,"s":[{"i":[[0,0],[0,0],[0,0],[0,0],[9.286,11.051],[7.454,2.388],[0,0],[0,0],[0,0]],"o":[[0,0],[0,0],[0,0],[0,0],[-3.603,-4.288],[-16,-5.125],[0,0],[0,0],[0,0]],"v":[[-122.5,-30.5],[-126,17.5],[18,28],[16.5,18],[-9.396,5.911],[16.5,-6.5],[17.5,-16.5],[7.5,-50],[-29,-38.5]],"c":true}]},{"i":{"x":0.833,"y":0.833},"o":{"x":0.167,"y":0.167},"t":11,"s":[{"i":[[0,0],[0,0],[0,0],[0,0],[9.286,11.051],[0,7.827],[0,0],[0,0],[0,0]],"o":[[0,0],[0,0],[0,0],[0,0],[-3.603,-4.288],[0,-28],[0,0],[0,0],[0,0]],"v":[[-131.5,-64.5],[-128.5,36.5],[17,32.5],[16.5,19.75],[-9.396,5.911],[-15.5,-12],[14.5,-42.75],[13,-57],[-24,-63]],"c":true}]},{"i":{"x":0.833,"y":0.833},"o":{"x":0.167,"y":0.167},"t":12,"s":[{"i":[[0,0],[0,0],[0,0],[27,0],[-41.076,18.761],[3.622,3.528],[-18,-1.25],[0,0],[0,0]],"o":[[0,0],[0,0],[0,0],[-27,0],[4.202,-1.919],[-38.5,-37.5],[19.5,0.25],[0,0],[0,0]],"v":[[-131.5,-64.5],[-125.5,69.5],[-25,76],[-4,49],[-30.924,8.739],[-18.875,-22],[13.5,-71.75],[-1.5,-89],[-47,-97.5]],"c":true}]},{"i":{"x":0.833,"y":0.833},"o":{"x":0.167,"y":0.167},"t":13,"s":[{"i":[[0,0],[0,0],[0,0],[37.507,-0.67],[-48.576,0.511],[21.501,-0.473],[-59.5,-0.25],[0,0],[0,0]],"o":[[0,0],[0,0],[0,0],[-56,1],[4.619,-0.049],[-45.5,1],[19.5,0.25],[0,0],[0,0]],"v":[[-131.5,-64.5],[-128,96],[-25.5,106.5],[-39,79],[-46.924,9.489],[-48,-31.5],[-44.5,-101.75],[-22,-127],[-123.5,-118.5]],"c":true}]},{"i":{"x":0.833,"y":0.833},"o":{"x":0.167,"y":0.167},"t":14,"s":[{"i":[[0,0],[0,0],[0,0],[37.507,0.676],[-38.576,0.511],[21.505,0.136],[-44.5,1.5],[0,0],[0,0]],"o":[[0,0],[0,0],[0,0],[-55.5,-1],[19.179,-0.254],[-39.5,-0.25],[19.5,0.25],[0,0],[0,0]],"v":[[-131.5,-64.5],[-126,124.5],[-15.5,130.5],[-60.5,104],[-85.424,9.489],[-74.5,-31.75],[-80.5,-127.5],[-19,-140],[-122.5,-140.5]],"c":true}]},{"i":{"x":0.833,"y":0.833},"o":{"x":0.167,"y":0.167},"t":15,"s":[{"i":[[0,0],[0,0],[0,0],[37.502,-0.922],[-25.076,1.011],[21.487,-0.91],[-25.5,-1.25],[0,0],[0,0]],"o":[[0,0],[0,0],[0,0],[-30.5,0.75],[19.165,-0.773],[-29.5,1.25],[19.5,0.25],[0,0],[0,0]],"v":[[-131.5,-64.5],[-126,143.25],[-15.5,149.25],[-90.5,123.75],[-87.924,9.489],[-87,-31.75],[-90.5,-145],[-19,-150],[-122.5,-150.5]],"c":true}]},{"t":16,"s":[{"i":[[0,0],[0,0],[0,0],[37.502,-0.922],[-25.076,1.011],[21.487,-0.91],[-25.5,-1.25],[0,0],[0,0]],"o":[[0,0],[0,0],[0,0],[-30.5,0.75],[19.165,-0.773],[-29.5,1.25],[21,-5.5],[0,0],[0,0]],"v":[[-131.5,-64.5],[-126,143.25],[-15.5,149.25],[-90.5,123.25],[-87.924,9.489],[-87,-31.75],[-91.5,-147.5],[-20.5,-163.5],[-122.5,-150.5]],"c":true}]}],"ix":2},"nm":"Path 1","mn":"ADBE Vector Shape - Group","hd":false},{"ty":"st","c":{"a":0,"k":[0,0.188235294118,0.301960784314,1],"ix":3},"o":{"a":0,"k":100,"ix":4},"w":{"a":0,"k":3,"ix":5},"lc":1,"lj":1,"ml":4,"bm":0,"nm":"Stroke 1","mn":"ADBE Vector Graphic - Stroke","hd":false},{"ty":"fl","c":{"a":0,"k":[0,0.188235294118,0.301960784314,1],"ix":4},"o":{"a":0,"k":100,"ix":5},"r":1,"bm":0,"nm":"Fill 1","mn":"ADBE Vector Graphic - Fill","hd":false},{"ty":"tr","p":{"a":0,"k":[0,0],"ix":2},"a":{"a":0,"k":[0,0],"ix":1},"s":{"a":0,"k":[100,100],"ix":3},"r":{"a":0,"k":0,"ix":6},"o":{"a":0,"k":100,"ix":7},"sk":{"a":0,"k":0,"ix":4},"sa":{"a":0,"k":0,"ix":5},"nm":"Transform"}],"nm":"Shape 1","np":3,"cix":2,"bm":0,"ix":1,"mn":"ADBE Vector Group","hd":false}],"ip":10,"op":17,"st":0,"bm":0},{"ddd":0,"ind":16,"ty":4,"nm":"E_1","sr":1,"ks":{"o":{"a":0,"k":100,"ix":11},"r":{"a":0,"k":0,"ix":10},"p":{"a":0,"k":[212.183,155.027,0],"ix":2,"l":2},"a":{"a":1,"k":[{"i":{"x":0.667,"y":1},"o":{"x":0.333,"y":0},"t":8,"s":[-137.25,-115.25,0],"to":[0,26.833,0],"ti":[0,-17.708,0]},{"i":{"x":0.437,"y":1},"o":{"x":0.333,"y":0},"t":16,"s":[-137.25,45.75,0],"to":[0,17.708,0],"ti":[0,9.125,0]},{"t":23,"s":[-137.25,-9,0]}],"ix":1,"l":2},"s":{"a":0,"k":[81,81,100],"ix":6,"l":2}},"ao":0,"shapes":[{"ty":"gr","it":[{"ty":"rc","d":1,"s":{"a":1,"k":[{"i":{"x":[0.833,0.833],"y":[0.833,0.833]},"o":{"x":[0.167,0.167],"y":[0.167,0.167]},"t":0,"s":[0,0]},{"i":{"x":[0.833,0.833],"y":[0.833,0.833]},"o":{"x":[0.167,0.167],"y":[0.167,0.167]},"t":3,"s":[43,43]},{"t":8,"s":[43,184]}],"ix":2},"p":{"a":0,"k":[0,0],"ix":3},"r":{"a":0,"k":20,"ix":4},"nm":"Rectangle Path 1","mn":"ADBE Vector Shape - Rect","hd":false},{"ty":"fl","c":{"a":0,"k":[0,0.188235294118,0.301960784314,1],"ix":4},"o":{"a":0,"k":100,"ix":5},"r":1,"bm":0,"nm":"Fill 1","mn":"ADBE Vector Graphic - Fill","hd":false},{"ty":"tr","p":{"a":0,"k":[-195.5,7.5],"ix":2},"a":{"a":0,"k":[0,0],"ix":1},"s":{"a":0,"k":[100,100],"ix":3},"r":{"a":0,"k":90,"ix":6},"o":{"a":0,"k":100,"ix":7},"sk":{"a":0,"k":0,"ix":4},"sa":{"a":0,"k":0,"ix":5},"nm":"Transform"}],"nm":"Rectangle 1","np":3,"cix":2,"bm":0,"ix":1,"mn":"ADBE Vector Group","hd":false}],"ip":0,"op":41,"st":8,"bm":0},{"ddd":0,"ind":17,"ty":4,"nm":"E_2","sr":1,"ks":{"o":{"a":0,"k":100,"ix":11},"r":{"a":0,"k":0,"ix":10},"p":{"a":0,"k":[194.363,155.027,0],"ix":2,"l":2},"a":{"a":0,"k":[-137.25,-115.25,0],"ix":1,"l":2},"s":{"a":0,"k":[81,81,100],"ix":6,"l":2}},"ao":0,"shapes":[{"ty":"gr","it":[{"ty":"rc","d":1,"s":{"a":0,"k":[43,132],"ix":2},"p":{"a":0,"k":[0,0],"ix":3},"r":{"a":0,"k":20,"ix":4},"nm":"Rectangle Path 1","mn":"ADBE Vector Shape - Rect","hd":false},{"ty":"fl","c":{"a":0,"k":[0,0.188235294118,0.301960784314,1],"ix":4},"o":{"a":0,"k":100,"ix":5},"r":1,"bm":0,"nm":"Fill 1","mn":"ADBE Vector Graphic - Fill","hd":false},{"ty":"tr","p":{"a":0,"k":[-195.5,7.5],"ix":2},"a":{"a":0,"k":[0,0],"ix":1},"s":{"a":0,"k":[100,100],"ix":3},"r":{"a":0,"k":90,"ix":6},"o":{"a":0,"k":100,"ix":7},"sk":{"a":0,"k":0,"ix":4},"sa":{"a":0,"k":0,"ix":5},"nm":"Transform"}],"nm":"Rectangle 1","np":3,"cix":2,"bm":0,"ix":1,"mn":"ADBE Vector Group","hd":false}],"ip":8,"op":41,"st":8,"bm":0},{"ddd":0,"ind":18,"ty":4,"nm":"E_3","sr":1,"ks":{"o":{"a":0,"k":100,"ix":11},"r":{"a":0,"k":0,"ix":10},"p":{"a":0,"k":[212.183,155.027,0],"ix":2,"l":2},"a":{"a":1,"k":[{"i":{"x":0.667,"y":1},"o":{"x":0.333,"y":0},"t":8,"s":[-137.25,-115.25,0],"to":[0,-26.167,0],"ti":[0,17.458,0]},{"i":{"x":0.437,"y":1},"o":{"x":0.333,"y":0},"t":16,"s":[-137.25,-272.25,0],"to":[0,-17.458,0],"ti":[0,-8.708,0]},{"t":23,"s":[-137.25,-220,0]}],"ix":1,"l":2},"s":{"a":0,"k":[81,81,100],"ix":6,"l":2}},"ao":0,"shapes":[{"ty":"gr","it":[{"ty":"rc","d":1,"s":{"a":1,"k":[{"i":{"x":[0.833,0.833],"y":[0.833,0.833]},"o":{"x":[0.167,0.167],"y":[0.167,0.167]},"t":0,"s":[0,0]},{"i":{"x":[0.833,0.833],"y":[0.833,0.833]},"o":{"x":[0.167,0.167],"y":[0.167,0.167]},"t":3,"s":[43,43]},{"t":8,"s":[43,184]}],"ix":2},"p":{"a":0,"k":[0,0],"ix":3},"r":{"a":0,"k":20,"ix":4},"nm":"Rectangle Path 1","mn":"ADBE Vector Shape - Rect","hd":false},{"ty":"fl","c":{"a":0,"k":[0,0.188235294118,0.301960784314,1],"ix":4},"o":{"a":0,"k":100,"ix":5},"r":1,"bm":0,"nm":"Fill 1","mn":"ADBE Vector Graphic - Fill","hd":false},{"ty":"tr","p":{"a":0,"k":[-195.5,7.5],"ix":2},"a":{"a":0,"k":[0,0],"ix":1},"s":{"a":0,"k":[100,100],"ix":3},"r":{"a":0,"k":90,"ix":6},"o":{"a":0,"k":100,"ix":7},"sk":{"a":0,"k":0,"ix":4},"sa":{"a":0,"k":0,"ix":5},"nm":"Transform"}],"nm":"Rectangle 1","np":3,"cix":2,"bm":0,"ix":1,"mn":"ADBE Vector Group","hd":false}],"ip":0,"op":41,"st":8,"bm":0},{"ddd":0,"ind":19,"ty":4,"nm":"E_4","sr":1,"ks":{"o":{"a":0,"k":100,"ix":11},"r":{"a":0,"k":0,"ix":10},"p":{"a":0,"k":[108.097,155.027,0],"ix":2,"l":2},"a":{"a":0,"k":[-195.25,-115.25,0],"ix":1,"l":2},"s":{"a":0,"k":[81,81,100],"ix":6,"l":2}},"ao":0,"shapes":[{"ty":"gr","it":[{"ty":"rc","d":1,"s":{"a":1,"k":[{"i":{"x":[0.833,0.833],"y":[0.833,0.833]},"o":{"x":[0.167,0.167],"y":[0.167,0.167]},"t":9,"s":[43,43]},{"i":{"x":[0.833,0.833],"y":[0.833,0.833]},"o":{"x":[0.167,0.167],"y":[0.167,0.167]},"t":12,"s":[43,182.125]},{"i":{"x":[0.833,0.833],"y":[0.833,0.833]},"o":{"x":[0.167,0.167],"y":[0.167,0.167]},"t":14,"s":[43,304.275]},{"i":{"x":[0.833,0.833],"y":[0.833,0.833]},"o":{"x":[0.167,0.167],"y":[0.167,0.167]},"t":17,"s":[43,350]},{"i":{"x":[0.833,0.833],"y":[0.833,0.833]},"o":{"x":[0.167,0.167],"y":[0.167,0.167]},"t":19,"s":[43,299.333]},{"i":{"x":[0.833,0.833],"y":[0.833,0.833]},"o":{"x":[0.167,0.167],"y":[0.167,0.167]},"t":20,"s":[43,258.75]},{"t":23,"s":[43,237]}],"ix":2},"p":{"a":0,"k":[0,0],"ix":3},"r":{"a":0,"k":20,"ix":4},"nm":"Rectangle Path 1","mn":"ADBE Vector Shape - Rect","hd":false},{"ty":"fl","c":{"a":0,"k":[0,0.188235294118,0.301960784314,1],"ix":4},"o":{"a":0,"k":100,"ix":5},"r":1,"bm":0,"nm":"Fill 1","mn":"ADBE Vector Graphic - Fill","hd":false},{"ty":"tr","p":{"a":0,"k":[-195.5,7.5],"ix":2},"a":{"a":0,"k":[0,0],"ix":1},"s":{"a":0,"k":[100,100],"ix":3},"r":{"a":0,"k":0,"ix":6},"o":{"a":0,"k":100,"ix":7},"sk":{"a":0,"k":0,"ix":4},"sa":{"a":0,"k":0,"ix":5},"nm":"Transform"}],"nm":"Rectangle 1","np":3,"cix":2,"bm":0,"ix":1,"mn":"ADBE Vector Group","hd":false}],"ip":8,"op":41,"st":8,"bm":0}],"markers":[]}