{"v":"5.8.1","fr":25,"ip":0,"op":75,"w":312,"h":500,"nm":"3","ddd":0,"assets":[],"layers":[{"ddd":0,"ind":1,"ty":4,"nm":"Color 02","sr":1,"ks":{"o":{"a":0,"k":0,"ix":11},"r":{"a":0,"k":0,"ix":10},"p":{"a":0,"k":[3.578,82.072,0],"ix":2,"l":2},"a":{"a":0,"k":[-191,-198,0],"ix":1,"l":2},"s":{"a":0,"k":[27.2,27.2,100],"ix":6,"l":2}},"ao":0,"shapes":[{"ty":"gr","it":[{"ty":"rc","d":1,"s":{"a":0,"k":[42,42],"ix":2},"p":{"a":0,"k":[0,0],"ix":3},"r":{"a":0,"k":0,"ix":4},"nm":"Rectangle Path 1","mn":"ADBE Vector Shape - Rect","hd":false},{"ty":"fl","c":{"a":0,"k":[0,0.188235294118,0.301960784314,1],"ix":4},"o":{"a":0,"k":100,"ix":5},"r":1,"bm":0,"nm":"Fill 1","mn":"ADBE Vector Graphic - Fill","hd":false},{"ty":"tr","p":{"a":0,"k":[-191,-198],"ix":2},"a":{"a":0,"k":[0,0],"ix":1},"s":{"a":0,"k":[100,100],"ix":3},"r":{"a":0,"k":0,"ix":6},"o":{"a":0,"k":100,"ix":7},"sk":{"a":0,"k":0,"ix":4},"sa":{"a":0,"k":0,"ix":5},"nm":"Transform"}],"nm":"Rectangle 1","np":3,"cix":2,"bm":0,"ix":1,"mn":"ADBE Vector Group","hd":false}],"ip":0,"op":88,"st":0,"bm":0},{"ddd":0,"ind":2,"ty":4,"nm":"Color 01","sr":1,"ks":{"o":{"a":0,"k":0,"ix":11},"r":{"a":0,"k":0,"ix":10},"p":{"a":0,"k":[3.578,68.744,0],"ix":2,"l":2},"a":{"a":0,"k":[-191,-198,0],"ix":1,"l":2},"s":{"a":0,"k":[27.2,27.2,100],"ix":6,"l":2}},"ao":0,"shapes":[{"ty":"gr","it":[{"ty":"rc","d":1,"s":{"a":0,"k":[42,42],"ix":2},"p":{"a":0,"k":[0,0],"ix":3},"r":{"a":0,"k":0,"ix":4},"nm":"Rectangle Path 1","mn":"ADBE Vector Shape - Rect","hd":false},{"ty":"fl","c":{"a":0,"k":[0,0.443137254902,0.701960784314,1],"ix":4},"o":{"a":0,"k":100,"ix":5},"r":1,"bm":0,"nm":"Fill 1","mn":"ADBE Vector Graphic - Fill","hd":false},{"ty":"tr","p":{"a":0,"k":[-191,-198],"ix":2},"a":{"a":0,"k":[0,0],"ix":1},"s":{"a":0,"k":[100,100],"ix":3},"r":{"a":0,"k":0,"ix":6},"o":{"a":0,"k":100,"ix":7},"sk":{"a":0,"k":0,"ix":4},"sa":{"a":0,"k":0,"ix":5},"nm":"Transform"}],"nm":"Rectangle 1","np":3,"cix":2,"bm":0,"ix":1,"mn":"ADBE Vector Group","hd":false}],"ip":0,"op":88,"st":0,"bm":0},{"ddd":0,"ind":3,"ty":3,"nm":"Null 30","sr":1,"ks":{"o":{"a":0,"k":0,"ix":11},"r":{"a":0,"k":0,"ix":10},"p":{"a":0,"k":[150,197,0],"ix":2,"l":2},"a":{"a":0,"k":[0,0,0],"ix":1,"l":2},"s":{"a":0,"k":[34,34,100],"ix":6,"l":2}},"ao":0,"ip":0,"op":75,"st":0,"bm":0},{"ddd":0,"ind":4,"ty":4,"nm":"Blob","parent":3,"sr":1,"ks":{"o":{"a":0,"k":100,"ix":11},"r":{"a":0,"k":0,"ix":10},"p":{"a":0,"k":[73.438,-81,0],"ix":2,"l":2},"a":{"a":0,"k":[0,0,0],"ix":1,"l":2},"s":{"a":0,"k":[100,100,100],"ix":6,"l":2}},"ao":0,"shapes":[{"ty":"gr","it":[{"ind":0,"ty":"sh","ix":1,"ks":{"a":1,"k":[{"i":{"x":0.833,"y":0.833},"o":{"x":0.5,"y":0},"t":12,"s":[{"i":[[0,0],[0,0],[52.411,-108.323]],"o":[[0,0],[0,0],[28.552,0]],"v":[[-196.091,-11.875],[124.334,-11.875],[-40.989,202.521]],"c":false}]},{"i":{"x":0.5,"y":1},"o":{"x":0.167,"y":0.167},"t":16,"s":[{"i":[[0,0],[0,0],[52.411,-108.323]],"o":[[0,0],[0,0],[28.552,0]],"v":[[-196.091,-11.875],[37.334,-11.875],[-40.989,202.521]],"c":false}]},{"t":20,"s":[{"i":[[0,0],[0,0],[52.411,-108.323]],"o":[[0,0],[0,0],[28.552,0]],"v":[[-196.091,-11.875],[60.334,-11.438],[-40.989,202.521]],"c":false}]}],"ix":2},"nm":"Path 1","mn":"ADBE Vector Shape - Group","hd":false},{"ind":1,"ty":"sh","ix":2,"ks":{"a":1,"k":[{"i":{"x":0.833,"y":0.833},"o":{"x":0.5,"y":0},"t":16,"s":[{"i":[[52.411,-108.323],[-30.368,-70.25],[159.101,0],[-55.455,96.486]],"o":[[28.552,0],[36.008,83.296],[-105.949,0],[0,0]],"v":[[-40.989,202.521],[83.931,285.25],[-70.539,543.938],[-183.982,325.514]],"c":false}]},{"i":{"x":0.5,"y":1},"o":{"x":0.167,"y":0.167},"t":22,"s":[{"i":[[52.411,-108.323],[-14.184,-66.57],[121.551,0],[-66.455,58.486]],"o":[[28.552,0],[17.632,82.75],[-105.949,0],[0,0]],"v":[[-40.989,202.521],[56.931,295.25],[-70.539,501.938],[-149.982,318.514]],"c":false}]},{"t":27,"s":[{"i":[[52.411,-108.323],[-19.975,-65.067],[121.551,0],[-14.999,52.497]],"o":[[28.552,0],[26.632,86.75],[-105.949,0],[0,0]],"v":[[-40.989,202.521],[65.931,290.25],[-70.988,516.938],[-188.982,361.514]],"c":false}]}],"ix":2},"nm":"Path 2","mn":"ADBE Vector Shape - Group","hd":false},{"ty":"st","c":{"a":0,"k":[0,0.188235297799,0.301960796118,1],"ix":3},"o":{"a":0,"k":100,"ix":4},"w":{"a":0,"k":60,"ix":5},"lc":2,"lj":2,"bm":0,"nm":"Stroke 1","mn":"ADBE Vector Graphic - Stroke","hd":false},{"ty":"tm","s":{"a":1,"k":[{"i":{"x":[0.26],"y":[0.755]},"o":{"x":[0.8],"y":[0]},"t":7,"s":[0]},{"i":{"x":[0.5],"y":[1]},"o":{"x":[0.74],"y":[0.08]},"t":17,"s":[37]},{"t":23,"s":[100]}],"ix":1},"e":{"a":1,"k":[{"i":{"x":[0.26],"y":[0.755]},"o":{"x":[0.8],"y":[0]},"t":6,"s":[0]},{"i":{"x":[0.5],"y":[1]},"o":{"x":[0.74],"y":[0.08]},"t":16,"s":[37]},{"t":22,"s":[100]}],"ix":2},"o":{"a":0,"k":0,"ix":3},"m":2,"ix":4,"nm":"Trim Paths 1","mn":"ADBE Vector Filter - Trim","hd":false},{"ty":"tr","p":{"a":0,"k":[0,0],"ix":2},"a":{"a":0,"k":[0,0],"ix":1},"s":{"a":0,"k":[100,100],"ix":3},"r":{"a":0,"k":0,"ix":6},"o":{"a":0,"k":100,"ix":7},"sk":{"a":0,"k":0,"ix":4},"sa":{"a":0,"k":0,"ix":5},"nm":"Transform"}],"nm":"Shape 1","np":4,"cix":2,"bm":0,"ix":1,"mn":"ADBE Vector Group","hd":false},{"ty":"rp","c":{"a":0,"k":15,"ix":1},"o":{"a":0,"k":0,"ix":2},"m":1,"ix":2,"tr":{"ty":"tr","p":{"a":0,"k":[0.3,-0.9],"ix":2},"a":{"a":0,"k":[0,0],"ix":1},"s":{"a":0,"k":[100,100],"ix":3},"r":{"a":0,"k":0,"ix":4},"so":{"a":0,"k":100,"ix":5},"eo":{"a":0,"k":100,"ix":6},"nm":"Transform"},"nm":"Repeater 1","mn":"ADBE Vector Filter - Repeater","hd":false}],"ip":6,"op":75,"st":6,"bm":0},{"ddd":0,"ind":5,"ty":4,"nm":"Splash 2","parent":3,"sr":1,"ks":{"o":{"a":0,"k":100,"ix":11},"r":{"a":0,"k":-138.836,"ix":10},"p":{"a":0,"k":[-114,332,0],"ix":2,"l":2},"a":{"a":0,"k":[0,0,0],"ix":1,"l":2},"s":{"a":0,"k":[100,-100,100],"ix":6,"l":2}},"ao":0,"shapes":[{"ty":"gr","it":[{"ind":0,"ty":"sh","ix":1,"ks":{"a":0,"k":{"i":[[-71.149,26.718],[58.354,39.194],[-93.75,-77.136]],"o":[[159.428,-59.87],[-44.331,-29.776],[193.516,159.222]],"v":[[-2,0],[82.282,62.221],[206.363,34.919]],"c":false},"ix":2},"nm":"Path 1","mn":"ADBE Vector Shape - Group","hd":false},{"ty":"tm","s":{"a":1,"k":[{"i":{"x":[0],"y":[1]},"o":{"x":[0.001],"y":[0.001]},"t":21,"s":[0]},{"t":37,"s":[100]}],"ix":1},"e":{"a":1,"k":[{"i":{"x":[0],"y":[1]},"o":{"x":[0.001],"y":[0.001]},"t":20,"s":[0]},{"t":36,"s":[100]}],"ix":2},"o":{"a":0,"k":0,"ix":3},"m":1,"ix":2,"nm":"Trim Paths 1","mn":"ADBE Vector Filter - Trim","hd":false},{"ty":"st","c":{"a":0,"k":[0,0.188235297799,0.301960796118,1],"ix":3},"o":{"a":0,"k":100,"ix":4},"w":{"a":1,"k":[{"i":{"x":[0.22],"y":[1]},"o":{"x":[0.167],"y":[0.167]},"t":20,"s":[75]},{"t":37,"s":[0]}],"ix":5},"lc":2,"lj":1,"ml":4,"bm":0,"nm":"Stroke 2","mn":"ADBE Vector Graphic - Stroke","hd":false},{"ty":"tr","p":{"a":0,"k":[0,0],"ix":2},"a":{"a":0,"k":[0,0],"ix":1},"s":{"a":0,"k":[100,100],"ix":3},"r":{"a":0,"k":0,"ix":6},"o":{"a":0,"k":100,"ix":7},"sk":{"a":0,"k":0,"ix":4},"sa":{"a":0,"k":0,"ix":5},"nm":"Transform"}],"nm":"Shape 1","np":3,"cix":2,"bm":0,"ix":1,"mn":"ADBE Vector Group","hd":false}],"ip":20,"op":75,"st":20,"bm":0},{"ddd":0,"ind":6,"ty":4,"nm":"Splash","parent":3,"sr":1,"ks":{"o":{"a":0,"k":100,"ix":11},"r":{"a":0,"k":-105.758,"ix":10},"p":{"a":0,"k":[187,-90,0],"ix":2,"l":2},"a":{"a":0,"k":[0,0,0],"ix":1,"l":2},"s":{"a":0,"k":[100,100,100],"ix":6,"l":2}},"ao":0,"shapes":[{"ty":"gr","it":[{"ind":0,"ty":"sh","ix":1,"ks":{"a":0,"k":{"i":[[26.247,-71.324],[32.774,23.742]],"o":[[-26.319,71.52],[-72.117,-52.241]],"v":[[-2,0],[-113.131,45.546]],"c":false},"ix":2},"nm":"Path 1","mn":"ADBE Vector Shape - Group","hd":false},{"ty":"tm","s":{"a":1,"k":[{"i":{"x":[0],"y":[1]},"o":{"x":[0.001],"y":[0.001]},"t":12,"s":[0]},{"t":21,"s":[100]}],"ix":1},"e":{"a":1,"k":[{"i":{"x":[0],"y":[1]},"o":{"x":[0.001],"y":[0.001]},"t":11,"s":[0]},{"t":20,"s":[100]}],"ix":2},"o":{"a":0,"k":0,"ix":3},"m":1,"ix":2,"nm":"Trim Paths 1","mn":"ADBE Vector Filter - Trim","hd":false},{"ty":"st","c":{"a":0,"k":[0,0.188235297799,0.301960796118,1],"ix":3},"o":{"a":0,"k":100,"ix":4},"w":{"a":1,"k":[{"i":{"x":[0.274],"y":[1]},"o":{"x":[0.167],"y":[0.167]},"t":11,"s":[75]},{"t":23,"s":[0]}],"ix":5},"lc":2,"lj":1,"ml":4,"bm":0,"nm":"Stroke 2","mn":"ADBE Vector Graphic - Stroke","hd":false},{"ty":"tr","p":{"a":0,"k":[0,0],"ix":2},"a":{"a":0,"k":[0,0],"ix":1},"s":{"a":0,"k":[100,100],"ix":3},"r":{"a":0,"k":0,"ix":6},"o":{"a":0,"k":100,"ix":7},"sk":{"a":0,"k":0,"ix":4},"sa":{"a":0,"k":0,"ix":5},"nm":"Transform"}],"nm":"Shape 1","np":3,"cix":2,"bm":0,"ix":1,"mn":"ADBE Vector Group","hd":false}],"ip":11,"op":75,"st":11,"bm":0},{"ddd":0,"ind":7,"ty":4,"nm":"3","parent":3,"sr":1,"ks":{"o":{"a":0,"k":100,"ix":11},"r":{"a":0,"k":0,"ix":10},"p":{"a":0,"k":[73.438,-81,0],"ix":2,"l":2},"a":{"a":0,"k":[0,0,0],"ix":1,"l":2},"s":{"a":0,"k":[100,100,100],"ix":6,"l":2}},"ao":0,"shapes":[{"ty":"gr","it":[{"ind":0,"ty":"sh","ix":1,"ks":{"a":1,"k":[{"i":{"x":0.833,"y":0.833},"o":{"x":0.5,"y":0},"t":12,"s":[{"i":[[0,0],[0,0],[52.411,-108.323]],"o":[[0,0],[0,0],[28.552,0]],"v":[[-196.091,-11.875],[124.334,-11.875],[-40.989,202.521]],"c":false}]},{"i":{"x":0.5,"y":1},"o":{"x":0.167,"y":0.167},"t":16,"s":[{"i":[[0,0],[0,0],[52.411,-108.323]],"o":[[0,0],[0,0],[28.552,0]],"v":[[-196.091,-11.875],[37.334,-11.875],[-40.989,202.521]],"c":false}]},{"t":20,"s":[{"i":[[0,0],[0,0],[52.411,-108.323]],"o":[[0,0],[0,0],[28.552,0]],"v":[[-196.091,-11.875],[60.334,-11.438],[-40.989,202.521]],"c":false}]}],"ix":2},"nm":"Path 1","mn":"ADBE Vector Shape - Group","hd":false},{"ind":1,"ty":"sh","ix":2,"ks":{"a":1,"k":[{"i":{"x":0.833,"y":0.833},"o":{"x":0.5,"y":0},"t":16,"s":[{"i":[[52.411,-108.323],[-30.368,-70.25],[159.101,0],[-55.455,96.486]],"o":[[28.552,0],[36.008,83.296],[-105.949,0],[0,0]],"v":[[-40.989,202.521],[83.931,285.25],[-70.539,543.938],[-183.982,325.514]],"c":false}]},{"i":{"x":0.5,"y":1},"o":{"x":0.167,"y":0.167},"t":22,"s":[{"i":[[52.411,-108.323],[-14.184,-66.57],[121.551,0],[-66.455,58.486]],"o":[[28.552,0],[17.632,82.75],[-105.949,0],[0,0]],"v":[[-40.989,202.521],[56.931,295.25],[-70.539,501.938],[-149.982,318.514]],"c":false}]},{"t":27,"s":[{"i":[[52.411,-108.323],[-19.975,-65.067],[121.551,0],[-14.999,52.497]],"o":[[28.552,0],[26.632,86.75],[-105.949,0],[0,0]],"v":[[-40.989,202.521],[65.931,290.25],[-70.988,516.938],[-188.982,361.514]],"c":false}]}],"ix":2},"nm":"Path 2","mn":"ADBE Vector Shape - Group","hd":false},{"ty":"st","c":{"a":0,"k":[0,0.188235297799,0.301960796118,1],"ix":3},"o":{"a":0,"k":100,"ix":4},"w":{"a":0,"k":50,"ix":5},"lc":2,"lj":2,"bm":0,"nm":"Stroke 1","mn":"ADBE Vector Graphic - Stroke","hd":false},{"ty":"tm","s":{"a":1,"k":[{"i":{"x":[0],"y":[1]},"o":{"x":[0.5],"y":[0]},"t":6,"s":[0]},{"t":26,"s":[7.3]}],"ix":1},"e":{"a":1,"k":[{"i":{"x":[0.26],"y":[0.755]},"o":{"x":[0.8],"y":[0]},"t":6,"s":[0]},{"i":{"x":[0.5],"y":[1]},"o":{"x":[0.74],"y":[0.08]},"t":16,"s":[37]},{"t":22,"s":[100]}],"ix":2},"o":{"a":0,"k":0,"ix":3},"m":2,"ix":4,"nm":"Trim Paths 1","mn":"ADBE Vector Filter - Trim","hd":false},{"ty":"tm","s":{"a":0,"k":0,"ix":1},"e":{"a":0,"k":100,"ix":2},"o":{"a":0,"k":0,"ix":3},"m":2,"ix":5,"nm":"Trim Paths 2","mn":"ADBE Vector Filter - Trim","hd":false},{"ty":"tr","p":{"a":0,"k":[0,0],"ix":2},"a":{"a":0,"k":[0,0],"ix":1},"s":{"a":0,"k":[100,100],"ix":3},"r":{"a":0,"k":0,"ix":6},"o":{"a":0,"k":100,"ix":7},"sk":{"a":0,"k":0,"ix":4},"sa":{"a":0,"k":0,"ix":5},"nm":"Transform"}],"nm":"Shape 1","np":5,"cix":2,"bm":0,"ix":1,"mn":"ADBE Vector Group","hd":false},{"ty":"rp","c":{"a":0,"k":15,"ix":1},"o":{"a":0,"k":0,"ix":2},"m":1,"ix":2,"tr":{"ty":"tr","p":{"a":0,"k":[0.3,-0.9],"ix":2},"a":{"a":0,"k":[0,0],"ix":1},"s":{"a":0,"k":[100,100],"ix":3},"r":{"a":0,"k":0,"ix":4},"so":{"a":0,"k":100,"ix":5},"eo":{"a":0,"k":100,"ix":6},"nm":"Transform"},"nm":"Repeater 1","mn":"ADBE Vector Filter - Repeater","hd":false}],"ip":6,"op":75,"st":6,"bm":0},{"ddd":0,"ind":8,"ty":4,"nm":"Accent","parent":3,"sr":1,"ks":{"o":{"a":0,"k":100,"ix":11},"r":{"a":0,"k":0,"ix":10},"p":{"a":0,"k":[73.438,-81,0],"ix":2,"l":2},"a":{"a":0,"k":[0,0,0],"ix":1,"l":2},"s":{"a":0,"k":[100,100,100],"ix":6,"l":2}},"ao":0,"shapes":[{"ty":"gr","it":[{"ind":0,"ty":"sh","ix":1,"ks":{"a":1,"k":[{"i":{"x":0.833,"y":0.833},"o":{"x":0.5,"y":0},"t":6,"s":[{"i":[[0,0],[0,0],[52.411,-108.323]],"o":[[0,0],[0,0],[28.552,0]],"v":[[-196.091,-11.875],[124.334,-11.875],[-40.989,202.521]],"c":false}]},{"i":{"x":0.5,"y":1},"o":{"x":0.167,"y":0.167},"t":10,"s":[{"i":[[0,0],[0,0],[52.411,-108.323]],"o":[[0,0],[0,0],[28.552,0]],"v":[[-196.091,-11.875],[37.334,-11.875],[-40.989,202.521]],"c":false}]},{"t":14,"s":[{"i":[[0,0],[0,0],[52.411,-108.323]],"o":[[0,0],[0,0],[28.552,0]],"v":[[-196.091,-11.875],[60.334,-11.438],[-40.989,202.521]],"c":false}]}],"ix":2},"nm":"Path 1","mn":"ADBE Vector Shape - Group","hd":false},{"ind":1,"ty":"sh","ix":2,"ks":{"a":1,"k":[{"i":{"x":0.833,"y":0.833},"o":{"x":0.5,"y":0},"t":10,"s":[{"i":[[52.411,-108.323],[-30.368,-70.25],[159.101,0],[-55.455,96.486]],"o":[[28.552,0],[36.008,83.296],[-105.949,0],[0,0]],"v":[[-40.989,202.521],[83.931,285.25],[-70.539,543.938],[-183.982,325.514]],"c":false}]},{"i":{"x":0.5,"y":1},"o":{"x":0.167,"y":0.167},"t":16,"s":[{"i":[[52.411,-108.323],[-14.184,-66.57],[121.551,0],[-66.455,58.486]],"o":[[28.552,0],[17.632,82.75],[-105.949,0],[0,0]],"v":[[-40.989,202.521],[56.931,295.25],[-70.539,501.938],[-149.982,318.514]],"c":false}]},{"t":21,"s":[{"i":[[52.411,-108.323],[-19.975,-65.067],[121.551,0],[-14.999,52.497]],"o":[[28.552,0],[26.632,86.75],[-105.949,0],[0,0]],"v":[[-40.989,202.521],[65.931,290.25],[-70.988,516.938],[-188.982,361.514]],"c":false}]}],"ix":2},"nm":"Path 2","mn":"ADBE Vector Shape - Group","hd":false},{"ty":"st","c":{"a":0,"k":[0,0.443137258291,0.701960802078,1],"ix":3},"o":{"a":0,"k":100,"ix":4},"w":{"a":1,"k":[{"i":{"x":[0.833],"y":[0.833]},"o":{"x":[0.167],"y":[0.167]},"t":6,"s":[50]},{"i":{"x":[0.833],"y":[0.833]},"o":{"x":[0.167],"y":[0.167]},"t":7,"s":[75]},{"i":{"x":[0.833],"y":[0.833]},"o":{"x":[0.167],"y":[0.167]},"t":8,"s":[50]},{"i":{"x":[0.833],"y":[0.833]},"o":{"x":[0.167],"y":[0.167]},"t":10,"s":[75]},{"t":12,"s":[50]}],"ix":5},"lc":2,"lj":2,"bm":0,"nm":"Stroke 1","mn":"ADBE Vector Graphic - Stroke","hd":false},{"ty":"tm","s":{"a":1,"k":[{"i":{"x":[0.26],"y":[0.755]},"o":{"x":[0.8],"y":[0]},"t":2,"s":[0]},{"i":{"x":[0.5],"y":[1]},"o":{"x":[0.74],"y":[0.08]},"t":12,"s":[37]},{"t":18,"s":[100]}],"ix":1},"e":{"a":1,"k":[{"i":{"x":[0.26],"y":[0.755]},"o":{"x":[0.8],"y":[0]},"t":0,"s":[0]},{"i":{"x":[0.5],"y":[1]},"o":{"x":[0.74],"y":[0.08]},"t":10,"s":[37]},{"t":16,"s":[100]}],"ix":2},"o":{"a":0,"k":0,"ix":3},"m":2,"ix":4,"nm":"Trim Paths 1","mn":"ADBE Vector Filter - Trim","hd":false},{"ty":"tr","p":{"a":0,"k":[0,0],"ix":2},"a":{"a":0,"k":[0,0],"ix":1},"s":{"a":0,"k":[100,100],"ix":3},"r":{"a":0,"k":0,"ix":6},"o":{"a":0,"k":100,"ix":7},"sk":{"a":0,"k":0,"ix":4},"sa":{"a":0,"k":0,"ix":5},"nm":"Transform"}],"nm":"Shape 1","np":4,"cix":2,"bm":0,"ix":1,"mn":"ADBE Vector Group","hd":false},{"ty":"rp","c":{"a":0,"k":15,"ix":1},"o":{"a":0,"k":0,"ix":2},"m":1,"ix":2,"tr":{"ty":"tr","p":{"a":0,"k":[0.3,-0.9],"ix":2},"a":{"a":0,"k":[0,0],"ix":1},"s":{"a":0,"k":[100,100],"ix":3},"r":{"a":0,"k":0,"ix":4},"so":{"a":0,"k":100,"ix":5},"eo":{"a":0,"k":100,"ix":6},"nm":"Transform"},"nm":"Repeater 1","mn":"ADBE Vector Filter - Repeater","hd":false}],"ip":0,"op":75,"st":0,"bm":0}],"markers":[]}